openlist_sdk/__init__.py
openlist_sdk/client.py
openlist_sdk/config.py
openlist_sdk/utils.py
openlist_sdk/api/__init__.py
openlist_sdk/api/auth.py
openlist_sdk/api/fs.py
openlist_sdk/api/public.py
openlist_sdk/api/share.py
openlist_sdk/api/storage.py
openlist_sdk/api/task.py
openlist_sdk/api/admin/__init__.py
openlist_sdk/api/admin/driver.py
openlist_sdk/api/admin/index.py
openlist_sdk/api/admin/meta.py
openlist_sdk/api/admin/setting.py
openlist_sdk/api/admin/user.py
openlist_sdk/core/session.py
oplist_sdk-0.5.1.dist-info/METADATA
oplist_sdk-0.5.1.dist-info/WHEEL
oplist_sdk-0.5.1.dist-info/RECORD
