Metadata-Version: 2.4
Name: oplist-sdk
Version: 0.5.1
Summary: A powerful, type-safe Python SDK for OpenList API
Author-email: XingYuOu <ouxingyueee@163.com>
License-Expression: MIT
Keywords: alist,api,nas,openlist,sdk,storage
Classifier: Development Status :: 4 - Beta
Classifier: Intended Audience :: Developers
Classifier: License :: OSI Approved :: MIT License
Classifier: Programming Language :: Python :: 3.10
Classifier: Programming Language :: Python :: 3.11
Classifier: Programming Language :: Python :: 3.12
Classifier: Topic :: Internet :: WWW/HTTP
Classifier: Topic :: System :: Filesystems
Requires-Python: >=3.10
Requires-Dist: httpx>=0.24.0
Provides-Extra: dev
Requires-Dist: build; extra == 'dev'
Requires-Dist: pytest; extra == 'dev'
Requires-Dist: python-dotenv; extra == 'dev'
Requires-Dist: twine; extra == 'dev'
Provides-Extra: http2
Requires-Dist: httpx[http2]; extra == 'http2'
